sentinel_images_downloader/__init__.py
sentinel_images_downloader/auth.py
sentinel_images_downloader/downloader.py
sentinel_images_downloader/evalscripts.py
sentinel_images_downloader/utils.py
sentinel_images_downloader-0.1.0.dist-info/licenses/LICENSE.txt
sentinel_images_downloader-0.1.0.dist-info/METADATA
sentinel_images_downloader-0.1.0.dist-info/WHEEL
sentinel_images_downloader-0.1.0.dist-info/top_level.txt
sentinel_images_downloader-0.1.0.dist-info/RECORD
