Metadata-Version: 2.4
Name: sentinel_images_downloader
Version: 0.1.0
Summary: Download Sentinel-1 and Sentinel-2 images from Copernicus Data Space
Home-page: https://github.com/SaN4OuSl/sentinel_images_downloader
Author: SaN4OuSl
Author-email: oleksandr.laptiev.work@gmail.com
License: MIT
Classifier: Programming Language :: Python :: 3
Classifier: License :: OSI Approved :: MIT License
Classifier: Operating System :: OS Independent
Classifier: Topic :: Scientific/Engineering :: GIS
Requires-Python: >=3.7
License-File: LICENSE.txt
Requires-Dist: requests
Dynamic: author
Dynamic: author-email
Dynamic: classifier
Dynamic: description
Dynamic: description-content-type
Dynamic: home-page
Dynamic: license
Dynamic: license-file
Dynamic: requires-dist
Dynamic: requires-python
Dynamic: summary
